pyjavapropertiesu.py
pyjavaproperties_unicode-0.1.dist-info/DESCRIPTION.rst
pyjavaproperties_unicode-0.1.dist-info/METADATA
pyjavaproperties_unicode-0.1.dist-info/pydist.json
pyjavaproperties_unicode-0.1.dist-info/RECORD
pyjavaproperties_unicode-0.1.dist-info/top_level.txt
pyjavaproperties_unicode-0.1.dist-info/WHEEL
