Metadata-Version: 2.0
Name: pyjavaproperties-unicode
Version: 0.1
Summary: A small wrapper around pyjavaproperties to add unicode support.
Home-page: https://github.com/zerok/pyjavaproperties-unicode
Author: Horst Gutmann
Author-email: horst@zerokspot.com
License: MIT
Platform: UNKNOWN
Requires-Dist: pyjavaproperties (>=0.6)
